puuid/__init__.py
puuid/base.py
puuid/py.typed
puuid/sqlalchemy.py
puuid-1.1.0.dist-info/WHEEL
puuid-1.1.0.dist-info/METADATA
puuid-1.1.0.dist-info/RECORD
