Metadata-Version: 2.4
Name: pUUID
Version: 1.1.0
Summary: Prefixed UUIDs for Python with Pydantic & SQLAlchemy support.
Author: Jendrik Potyka, Fabian Preiss
Author-email: Jendrik Potyka <jpotyka@digon.io>, Fabian Preiss <fpreiss@digon.io>
License-Expression: LGPL-3.0-only
Classifier: Development Status :: 4 - Beta
Classifier: Intended Audience :: Developers
Classifier: License :: OSI Approved :: GNU Lesser General Public License v3 (LGPLv3)
Classifier: Programming Language :: Python :: 3.14
Classifier: Programming Language :: Python :: Implementation :: CPython
Classifier: Topic :: Software Development :: Libraries
Classifier: Topic :: Utilities
Classifier: Operating System :: OS Independent
Classifier: Typing :: Typed
Requires-Dist: pydantic>=2.12.5 ; extra == 'pydantic'
Requires-Dist: sqlalchemy>=2.0.45 ; extra == 'sqlalchemy'
Maintainer: Jendrik A. Potyka, Fabian A. Preiss
Maintainer-email: Jendrik A. Potyka <jpotyka@digon.io>, Fabian A. Preiss <fpreiss@digon.io>
Requires-Python: >=3.14
Provides-Extra: pydantic
Provides-Extra: sqlalchemy
